robot/__init__.py
robot/__main__.py
robot/errors.py
robot/libdoc.py
robot/logo.png
robot/pythonpathsetter.py
robot/rebot.py
robot/run.py
robot/testdoc.py
robot/version.py
robot/api/__init__.py
robot/api/deco.py
robot/api/exceptions.py
robot/api/interfaces.py
robot/api/logger.py
robot/api/parsing.py
robot/api/py.typed
robot/api/types.py
robot/conf/__init__.py
robot/conf/gatherfailed.py
robot/conf/languages.py
robot/conf/settings.py
robot/htmldata/__init__.py
robot/htmldata/htmlfilewriter.py
robot/htmldata/jsonwriter.py
robot/htmldata/template.py
robot/htmldata/common/__init__.py
robot/htmldata/common/js_disabled.css
robot/htmldata/common/storage.js
robot/htmldata/lib/__init__.py
robot/htmldata/lib/jquery.highlight.min.js
robot/htmldata/lib/jquery.min.js
robot/htmldata/lib/jquery.tablesorter.min.js
robot/htmldata/lib/jquery.tmpl.min.js
robot/htmldata/lib/jsxcompressor.min.js
robot/htmldata/libdoc/__init__.py
robot/htmldata/libdoc/libdoc.html
robot/htmldata/rebot/__init__.py
robot/htmldata/rebot/common.css
robot/htmldata/rebot/doc_formatting.css
robot/htmldata/rebot/fileloading.js
robot/htmldata/rebot/log.css
robot/htmldata/rebot/log.html
robot/htmldata/rebot/log.js
robot/htmldata/rebot/model.js
robot/htmldata/rebot/print.css
robot/htmldata/rebot/report.css
robot/htmldata/rebot/report.html
robot/htmldata/rebot/testdata.js
robot/htmldata/rebot/util.js
robot/htmldata/rebot/view.js
robot/htmldata/testdoc/__init__.py
robot/htmldata/testdoc/testdoc.css
robot/htmldata/testdoc/testdoc.html
robot/libdocpkg/__init__.py
robot/libdocpkg/builder.py
robot/libdocpkg/consoleviewer.py
robot/libdocpkg/datatypes.py
robot/libdocpkg/htmlutils.py
robot/libdocpkg/htmlwriter.py
robot/libdocpkg/jsonbuilder.py
robot/libdocpkg/jsonwriter.py
robot/libdocpkg/languages.py
robot/libdocpkg/model.py
robot/libdocpkg/output.py
robot/libdocpkg/robotbuilder.py
robot/libdocpkg/standardtypes.py
robot/libdocpkg/writer.py
robot/libdocpkg/xmlbuilder.py
robot/libdocpkg/xmlwriter.py
robot/libraries/BuiltIn.py
robotframework-7.4.dist-info/AUTHORS.rst
robotframework-7.4.dist-info/LICENSE.txt
robotframework-7.4.dist-info/METADATA
robotframework-7.4.dist-info/WHEEL
robotframework-7.4.dist-info/entry_points.txt
robotframework-7.4.dist-info/top_level.txt
robotframework-7.4.dist-info/RECORD
