Metadata-Version: 2.1
Name: robotframework
Version: 7.4
Summary: Generic automation framework for acceptance testing and robotic process automation (RPA)
Home-page: https://robotframework.org
Download-URL: https://pypi.org/project/robotframework
Author: Pekka Klärck
Author-email: peke@eliga.fi
License: Apache License 2.0
Project-URL: Source, https://github.com/robotframework/robotframework
Project-URL: Issue Tracker, https://github.com/robotframework/robotframework/issues
Project-URL: Documentation, https://robotframework.org/robotframework
Project-URL: Release Notes, https://github.com/robotframework/robotframework/blob/master/doc/releasenotes/rf-7.4.rst
Project-URL: Slack, http://slack.robotframework.org
Keywords: robotframework automation testautomation rpa testing acceptancetesting atdd bdd
Platform: any
Classifier: Development Status :: 5 - Production/Stable
Classifier: License :: OSI Approved :: Apache Software License
Classifier: Operating System :: OS Independent
Classifier: Programming Language :: Python :: 3
Classifier: Programming Language :: Python :: 3 :: Only
Classifier: Programming Language :: Python :: 3.8
Classifier: Programming Language :: Python :: 3.9
Classifier: Programming Language :: Python :: 3.10
Classifier: Programming Language :: Python :: 3.11
Classifier: Programming Language :: Python :: 3.12
Classifier: Programming Language :: Python :: 3.13
Classifier: Programming Language :: Python :: 3.14
Classifier: Programming Language :: Python :: Implementation :: CPython
Classifier: Programming Language :: Python :: Implementation :: PyPy
Classifier: Topic :: Software Development :: Testing
Classifier: Topic :: Software Development :: Testing :: Acceptance
Classifier: Topic :: Software Development :: Testing :: BDD
Classifier: Framework :: Robot Framework
Requires-Python: >=3.8
License-File: LICENSE.txt
License-File: AUTHORS.rst
